[
  {
    "type": "header",
    "command": "Export data to Json"
  },
  {
    "exported_time": "2023-09-01T18:09:45.2365524Z",
    "host": "192.168.101.61:5017",
    "db_properties": [
      {
        "name": "server",
        "value": "server=192.168.102.61"
      },
      {
        "name": "port",
        "value": "1433"
      },
      {
        "name": "database",
        "value": "cms"
      },
      {
        "name": "entity",
        "value": "Form"
      }
    ],
    "exported_by_fields": [
      {
        "form_id": null,
        "app": null
      }
    ]
  },
  {
    "type": "data",
    "data": [
      {
        "info": "{\"title\":\"MTG_ACC_CHILD_other_paper_infomation\",\"des\":\"MTG_ACC_CHILD_other_paper_infomation\",\"data\":\"\",\"learnapi\":\"\",\"learnsql\":\"\",\"bodata\":\"\",\"openOne\":\"true\",\"url_input\":\"\",\"lang_form\":{\"en\":\"MTG_ACC_CHILD_other_paper_infomation\"},\"mode_form\":{\"mode\":\"\",\"col_text\":\"\",\"col_input\":\"\"},\"form_code\":\"MTG_ACC_CHILD_other_paper_infomation\",\"ruleStrong\":[{\"code\":\"visibility\",\"config\":{\"component_event\":\"on_click\",\"component_action\":\"add;modify\",\"component_result\":\"apply\",\"condition\":\"\",\"visible\":\"true\",\"ena_dis\":\"false\",\"view_result\":\"code\"},\"inUse\":true,\"order\":1,\"isStart\":true},{\"code\":\"visibility\",\"config\":{\"component_event\":\"on_click\",\"component_action\":\"apply\",\"component_result\":\"apply\",\"condition\":\"\",\"visible\":\"not_use\",\"ena_dis\":\"true\",\"view_result\":\"code\"},\"inUse\":true,\"order\":1,\"isStart\":true},{\"code\":\"visibility\",\"config\":{\"component_event\":\"on_click\",\"component_action\":\"add\",\"component_result\":\"add\",\"condition\":\"\",\"visible\":\"not_use\",\"ena_dis\":\"true\",\"view_result\":\"\"},\"inUse\":true,\"order\":1,\"isStart\":false},{\"code\":\"visibility\",\"config\":{\"component_event\":\"on_click\",\"component_action\":\"apply\",\"component_result\":\"add\",\"condition\":\"\",\"visible\":\"not_use\",\"ena_dis\":\"false\",\"view_result\":\"\"},\"inUse\":true,\"order\":1},{\"code\":\"setValue\",\"config\":{\"component_event\":\"all\",\"component_action\":\"detail_customer_code\",\"component_result\":\"\",\"isGetOOP\":\"true\",\"getOOPFormat\":\"{\\n    \\\"dcustomerid\\\": \\\"lkp_data_mcustomercd.2\\\",\\n    \\\"name\\\": \\\"lkp_data_mcustomercd.1\\\"\\n}\"},\"inUse\":true,\"order\":1,\"isStart\":true},{\"code\":\"visibility\",\"config\":{\"component_event\":\"on_change\",\"component_action\":\"\",\"component_result\":\"dcustomerid;name;lkgid\",\"condition\":\"\",\"visible\":\"false\",\"ena_dis\":\"not_use\",\"view_result\":\"\"},\"inUse\":true,\"order\":1,\"isStart\":true}],\"app\":\"\"}",
        "list_layout": "[{\"name\":\"\",\"des\":\"\",\"class\":\"\",\"codeHidden\":\"2016bef2e4e3edbe\",\"inputtype\":\"cLayout\",\"list_view\":[{\"name\":\"M?u view\",\"code\":\"code\",\"codeHidden\":\"1aee1cb6ec37f32b\",\"inputtype\":\"cView\",\"isTab\":\"false\",\"list_input\":[{\"default\":{\"name\":\"Other paper type\",\"code\":\"Other paper type\",\"codeHidden\":\"0c9e8a134d292987\",\"class\":\"                                   col-xl-4 col-lg-4 col-md-5 col-sm-6 offset-xl-2-right offset-lg-2-right offset-md-1-right\",\"condition\":\"\",\"ofgroup\":\"\",\"class_ofgroup\":\"col-sm-12 col-md-12\",\"role\":\"\"},\"config\":{\"structable\":\"form_child.t\",\"structable_read\":\"form_child.t\",\"cdlist\":{\"query\":\"select c_cdlist.cdid,c_cdlist.cdname,c_cdlist.caption,c_cdlist.cdval,c_cdlist.cdidx from c_cdlist where wf.c_cdlist.cdgrp==='MTG'&&wf.c_cdlist.cdname==='PPTYPE' orderby c_cdlist.cdidx\",\"cdgrp\":\"MTG\",\"cdname\":\"PPTYPE\"},\"data_default\":\"\",\"data_mode\":\"cdlist\",\"query_data\":\"select c_cdlist.cdid,c_cdlist.cdname,c_cdlist.caption,c_cdlist.cdval,c_cdlist.cdidx from c_cdlist where wf.c_cdlist.cdgrp==='MTG'&&wf.c_cdlist.cdname==='PPTYPE' orderby c_cdlist.cdidx\",\"is_multi_select\":\"false\",\"is_multi_col\":\"false\",\"get_data_format\":\"c_cdlist.cdid\",\"selected_view_format\":\"@c_cdlist.caption\",\"table_format\":\"[\\n    {\\n        \\\"title\\\": \\\"Code\\\",\\n        \\\"code\\\": \\\"form_child_ifc_code.ifccd\\\"\\n    },\\n    {\\n        \\\"title\\\": \\\"Name\\\",\\n        \\\"code\\\": \\\"form_child_ifc_code.ifcname\\\"\\n    }\\n]\",\"col_format\":\"@c_cdlist.caption\",\"json_data\":\"[]\",\"key_selected\":\"c_cdlist.cdid\",\"useAction\":\"false\",\"isAutoDefault\":\"true\"},\"role\":{\"disabled\":\"\",\"visible\":\"\",\"other\":\"\",\"other2\":\"\"},\"property\":{},\"validate\":{\"request\":false},\"lang\":{\"ui\":{\"vi\":{\"Other paper type\":\"Other paper type\"},\"en\":{\"Other paper type\":\"Other paper type\"}}},\"configAVD\":{},\"inputtype\":\"jSelect\"},{\"default\":{\"name\":\"Other paper no\",\"code\":\"Other paper no\",\"codeHidden\":\"7ffc5fcf332a2418\",\"class\":\"                                   col-xl-4 col-lg-4 col-md-5 col-sm-6 offset-xl-2-right offset-lg-2-right offset-md-1-right\",\"condition\":\"\",\"ofgroup\":\"\",\"class_ofgroup\":\"col-sm-12 col-md-12\",\"role\":\"\"},\"config\":{\"action\":\"\",\"structable\":\"form_child.n\",\"structable_read\":\"form_child.n\",\"data_default\":\"\",\"isLookup\":\"false\",\"callform\":\"\",\"callform_detail\":\"\",\"callform_detail_mode\":\"modal\",\"data_view\":\"\",\"data_value\":\"\",\"is_disabled\":\"false\",\"autoWrap\":true,\"isSearch\":false},\"role\":{\"visible\":\"\",\"disabled\":\"\"},\"property\":{},\"validate\":{\"request\":false},\"lang\":{\"ui\":{\"vi\":{\"Linkage type\":\"Linkage type\"},\"en\":{\"Linkage type\":\"Linkage type\"},\"lo\":{\"Linkage type\":\"Linkage type\"},\"km\":{\"Linkage type\":\"Linkage type\"},\"th\":{\"Linkage type\":\"Linkage type\"},\"mg\":{\"Linkage type\":\"Linkage type\"},\"ja\":{\"Linkage type\":\"Linkage type\"},\"ko\":{\"Linkage type\":\"Linkage type\"}}},\"configAVD\":{},\"inputtype\":\"cTextInput\"},{\"default\":{\"name\":\"Other paper amount\",\"code\":\"Other paper amount\",\"codeHidden\":\"c6b846d2c196ac28\",\"class\":\"                                   col-xl-4 col-lg-4 col-md-5 col-sm-6 offset-xl-2-right offset-lg-2-right offset-md-1-right\",\"condition\":\"\",\"ofgroup\":\"\",\"class_ofgroup\":\"col-sm-12 col-md-12\",\"role\":\"\"},\"config\":{\"structable\":\"form_child.pamt\",\"structable_read\":\"form_child.pamt\",\"data_default\":0,\"format\":\"#,###.00\",\"decimal_length\":\"2\"},\"role\":{\"visible\":\"\",\"disabled\":\"\"},\"property\":{},\"validate\":{\"request\":false,\"min\":0},\"lang\":{},\"configAVD\":{},\"inputtype\":\"jCurrency\"}]},{\"name\":\"M?u view\",\"code\":\"code\",\"codeHidden\":\"ed54c39ee7144f0b\",\"inputtype\":\"cView\",\"isTab\":\"false\",\"list_input\":[{\"default\":{\"name\":\"Add\",\"code\":\"add\",\"codeHidden\":\"p5685f65655469i59\",\"class\":\"\",\"condition\":\"\",\"ofgroup\":\"\",\"class_ofgroup\":\"col-sm-12 col-md-12\",\"role\":\"\"},\"config\":{\"action\":\"default_save\",\"txFoActions\":\"[\\n    {\\n        \\\"function\\\": \\\"\\\",\\n        \\\"status\\\": \\\"A\\\",\\n        \\\"para\\\": []\\n    }\\n]\",\"txFo\":\"[\\n    {\\n        \\\"txcode\\\": \\\"#sys:fo-clearDataFormChild\\\",\\n        \\\"input\\\": {\\n            \\\"node_clear\\\": \\\"form_child\\\"\\n        }\\n    }\\n]\",\"useAction\":\"false\",\"icon\":\"fa-plus\",\"color\":\"primary\",\"onTable\":\"\",\"isMasterData\":\"false\",\"tableMasterData\":\"word_typing\",\"privateKeyTableMasterData\":\"id\"},\"role\":{\"visible\":\"\",\"disabled\":\"\"},\"property\":{\"danger\":\"\",\"warning\":\"\"},\"validate\":{},\"lang\":{},\"configAVD\":{},\"inputtype\":\"cButton\"},{\"default\":{\"name\":\"Apply\",\"code\":\"apply\",\"codeHidden\":\"3261a21a29bfc6f5\",\"class\":\"\",\"condition\":\"\",\"ofgroup\":\"\",\"class_ofgroup\":\"col-sm-12 col-md-12\",\"role\":\"\"},\"config\":{\"action\":\"\",\"txFoActions\":\"[\\n    {\\n        \\\"function\\\": \\\"\\\",\\n        \\\"status\\\": \\\"A\\\",\\n        \\\"para\\\": []\\n    }\\n]\",\"txFo\":\"[\\n    {\\n        \\\"txcode\\\": \\\"#sys:fo-saveDataFormChild\\\",\\n        \\\"input\\\": {\\n            \\\"node_get\\\": \\\"form_child\\\",\\n            \\\"node_set\\\": \\\"opaper\\\"\\n        }\\n    }\\n]\",\"useAction\":\"false\",\"icon\":\"fa-floppy-o\",\"color\":\"success\",\"onTable\":\"\",\"isMasterData\":\"false\",\"tableMasterData\":\"\",\"privateKeyTableMasterData\":\"\"},\"role\":{\"visible\":\"\",\"disabled\":\"\"},\"property\":{\"danger\":\"\",\"warning\":\"\"},\"validate\":{},\"lang\":{},\"configAVD\":{},\"inputtype\":\"cButton\"}]}]},{\"name\":\"\",\"des\":\"\",\"class\":\"\",\"codeHidden\":\"9379b68931989d66\",\"inputtype\":\"cLayout\",\"list_view\":[{\"name\":\"M?u view\",\"code\":\"formchild\",\"codeHidden\":\"1cacae7586c074d8\",\"inputtype\":\"cView\",\"isTab\":\"false\",\"list_input\":[{\"default\":{\"name\":\"Modify\",\"code\":\"modify\",\"codeHidden\":\"p6d988np4t55480\",\"class\":\"\",\"condition\":\"\",\"ofgroup\":\"\",\"class_ofgroup\":\"col-sm-12 col-md-12\",\"role\":\"\"},\"config\":{\"action\":\"default_view\",\"txFoActions\":\"[\\n    {\\n        \\\"function\\\": \\\"\\\",\\n        \\\"status\\\": \\\"A\\\",\\n        \\\"para\\\": []\\n    }\\n]\",\"txFo\":\"[\\n    {\\n        \\\"txcode\\\": \\\"#sys:fo-selectDataFormChild\\\",\\n        \\\"input\\\": {\\n            \\\"node_set\\\": \\\"form_child\\\"\\n        }\\n    }\\n]\",\"useAction\":\"false\",\"icon\":\"fa-edit\",\"color\":\"warning\",\"onTable\":\"table\",\"isMasterData\":\"true\",\"tableMasterData\":\"word_typing\",\"privateKeyTableMasterData\":\"id\"},\"role\":{\"visible\":\"\",\"disabled\":\"\"},\"property\":{\"danger\":\"\",\"warning\":\"\"},\"validate\":{},\"lang\":{},\"configAVD\":{},\"inputtype\":\"cButton\"},{\"default\":{\"name\":\"Remove\",\"code\":\"sp5549k86j7u5575\",\"codeHidden\":\"sp5555D4c33A84j\",\"class\":\"\",\"condition\":\"\",\"ofgroup\":\"\",\"class_ofgroup\":\"col-sm-12 col-md-12\",\"role\":\"\"},\"config\":{\"action\":\"default_delete\",\"txFoActions\":\"[\\n    {\\n        \\\"function\\\": \\\"\\\",\\n        \\\"status\\\": \\\"A\\\",\\n        \\\"para\\\": []\\n    }\\n]\",\"txFo\":\"[\\n    {\\n        \\\"txcode\\\": \\\"#sys:fo-removeDataFormChild\\\",\\n        \\\"input\\\": {\\n            \\\"node_table\\\": \\\"opaper\\\"\\n        }\\n    }\\n]\",\"useAction\":\"false\",\"icon\":\"fa-trash\",\"color\":\"danger\",\"onTable\":\"table\",\"isMasterData\":\"true\",\"tableMasterData\":\"word_typing\",\"privateKeyTableMasterData\":\"id\"},\"role\":{\"visible\":\"\",\"disabled\":\"\"},\"property\":{\"danger\":\"\",\"warning\":\"\"},\"validate\":{},\"lang\":{},\"configAVD\":{},\"inputtype\":\"cButton\"},{\"default\":{\"name\":\"\",\"code\":\"table\",\"codeHidden\":\"p6d5o69he73n34\",\"class\":\"col-12\",\"condition\":\"\",\"ofgroup\":\"\",\"class_ofgroup\":\"col-sm-12 col-md-12\",\"role\":\"\"},\"config\":{\"structable\":\"form_child.opaper\",\"query_data\":\"mtg_account_information.opaper\",\"paging_record\":\"5\",\"columns\":\"[\\n    {\\n        \\\"code\\\": \\\"opaper.t\\\",\\n        \\\"title\\\": \\\"Paper type\\\",\\n        \\\"inputtype\\\": \\\"ColumnString\\\",\\n        \\\"config\\\": {}\\n    },\\n    {\\n        \\\"code\\\": \\\"opaper.n\\\",\\n        \\\"title\\\": \\\"Paper No.\\\",\\n        \\\"inputtype\\\": \\\"ColumnString\\\",\\n        \\\"config\\\": {}\\n    },\\n    {\\n        \\\"code\\\": \\\"opaper.pamt\\\",\\n        \\\"title\\\": \\\"Other Paper Amount\\\",\\n        \\\"inputtype\\\": \\\"columnCurrency\\\",\\n        \\\"config\\\": {\\n            \\\"decimal\\\": 2\\n        }\\n    }\\n]\",\"hasPaging\":\"false\"},\"role\":{},\"property\":{},\"validate\":{},\"lang\":{\"vi\":{\"Paper type\":\"Paper type\",\"Paper No.\":\"Paper No.\",\"Other Paper Amount\":\"Other Paper Amount\"},\"en\":{\"Paper type\":\"Paper type\",\"Paper No.\":\"Paper No.\",\"Other Paper Amount\":\"Other Paper Amount\"}},\"configAVD\":{},\"inputtype\":\"jTableForm\"}]}]}]",
        "react_txt": "",
        "form_id": "MTG_ACC_CHILD_other_paper_infomation",
        "app": "ncbsCbs",
        "id": 610
      }
    ]
  }
]